{
  "$schema": "km_combine_kc100_parts_v1",
  "version": "1.0.0",
  "created_at": "2026-05-29",
  "source_pdf": "KC100_부품명세서.pdf",
  "machine": {
    "manufacturer": "KM",
    "manufacturer_ko": "국제종합기계 (주)",
    "category": "combine",
    "category_ko": "콤바인",
    "model": "KC100",
    "published": "2013-08",
    "total_pages": 558,
    "language": "ko",
    "manual_type_ko": "부품명세서 (Parts Catalog)"
  },
  "ordering_info_ko": {
    "note": "부품 주문 시 필요 정보: 도해 그림번호 = 부품목록 번호, 형식·품번·품명·수량·적용시점 기재",
    "return_policy": "오발송분 이외 반품 불가",
    "genuine_parts": "반드시 국제 순정부품 사용 (유사품 사용 시 조기파손 위험)"
  },
  "assembly_groups": [
    {"group":"1","name_ko":"엔진취부","page":17},
    {"group":"2","name_ko":"엔진취부대","page":18},
    {"group":"3","name_ko":"엔진콘트롤","page":19},
    {"group":"4","name_ko":"엔진전장","page":20},
    {"group":"5","name_ko":"연료탱크","page":22},
    {"group":"5B","name_ko":"연료탱크 B형","page":24},
    {"group":"6","name_ko":"에어클리너","page":26},
    {"group":"7","name_ko":"머플러","page":28},
    {"group":"8","name_ko":"라디에이터","page":30},
    {"group":"9","name_ko":"예취 구동 케이스","page":32},
    {"group":"10","name_ko":"예취축 A","page":34},
    {"group":"11","name_ko":"예취축 B","page":35},
    {"group":"12","name_ko":"예취축 C","page":36},
    {"group":"13","name_ko":"크랭크 축","page":38},
    {"group":"14","name_ko":"인구 종구동","page":40},
    {"group":"15","name_ko":"인기 횡구동축","page":44},
    {"group":"16","name_ko":"인기 축","page":46},
    {"group":"17","name_ko":"인기변속","page":48},
    {"group":"18","name_ko":"좌측인기 케이스","page":50},
    {"group":"19","name_ko":"우측인기 케이스","page":52},
    {"group":"21","name_ko":"우측인기 체인롤러","page":56},
    {"group":"22","name_ko":"좌측인기 체인롤러","page":58},
    {"group":"23","name_ko":"중간인기 체인롤러","page":60},
    {"group":"24","name_ko":"프런트 커버","page":62},
    {"group":"25","name_ko":"예취커버","page":64},
    {"group":"28","name_ko":"예취날 구동","page":70},
    {"group":"29","name_ko":"예취날","page":72},
    {"group":"30","name_ko":"분초판","page":74},
    {"group":"35","name_ko":"끌어모음벨트 (중우1)","page":84},
    {"group":"35-1","name_ko":"끌어모음벨트 (중우2)","page":86},
    {"group":"35-2","name_ko":"끌어모음벨트 (중좌1)","page":88},
    {"group":"35-3","name_ko":"끌어모음벨트 (중좌2)","page":90},
    {"group":"36","name_ko":"우측끌어모음벨트","page":92},
    {"group":"37","name_ko":"끌어모음벨트 (좌)","page":94},
    {"group":"74","name_ko":"요동 벨트","page":164},
    {"group":"77","name_ko":"탈곡통 벨트","page":170},
    {"group":"78","name_ko":"짚배출 벨트","page":172},
    {"group":"80","name_ko":"탈곡 클러치","page":175},
    {"group":"81","name_ko":"탈곡 입력 케이스","page":176},
    {"group":"82","name_ko":"탈곡통 구동 케이스","page":177},
    {"group":"83","name_ko":"피드체인 케이스","page":178},
    {"group":"84","name_ko":"짚배출 구동 케이스","page":179},
    {"group":"89","name_ko":"탈곡통","page":188},
    {"group":"92","name_ko":"처리통","page":194},
    {"group":"142","name_ko":"배관","page":288},
    {"group":"144","name_ko":"HST 배관","page":290},
    {"group":"146","name_ko":"상하 밸브","page":292},
    {"group":"147","name_ko":"상하 유압 실린더","page":294},
    {"group":"151","name_ko":"차체프레임","page":304},
    {"group":"155","name_ko":"아이들러","page":308},
    {"group":"156","name_ko":"트랙롤러","page":310},
    {"group":"157","name_ko":"이퀄라이저","page":312},
    {"group":"158","name_ko":"크롤러","page":314},
    {"group":"160","name_ko":"주행롤러","page":316},
    {"group":"166","name_ko":"램프","page":326},
    {"group":"167","name_ko":"방향지시등","page":328},
    {"group":"168","name_ko":"스위치","page":330},
    {"group":"170","name_ko":"경보 센서","page":334},
    {"group":"172","name_ko":"배터리","page":336},
    {"group":"173","name_ko":"와이어 하니스","page":338}
  ],
  "key_consumable_parts": [
    {"id":"PT-001","group":"6","name_ko":"에어클리너","part_number":"CA00003027A","qty":1,"type_ko":"필터"},
    {"id":"PT-002","group":"6","name_ko":"흡기호스 A","part_number":"CA00003055A","qty":1,"type_ko":"호스"},
    {"id":"PT-003","group":"29","name_ko":"예취날 총조합","part_number":"CA00003091B","qty":1,"type_ko":"예취날","remark":"2013년식"},
    {"id":"PT-004","group":"29","name_ko":"예취날 R 조합","part_number":"CA00007314B","qty":1,"type_ko":"예취날","remark":"2013년식"},
    {"id":"PT-005","group":"29","name_ko":"예취날 L 조합","part_number":"CA00003081D","qty":1,"type_ko":"예취날","remark":"2013년식"},
    {"id":"PT-006","group":"35","name_ko":"V벨트 LB-108","part_number":"CA00008464A","qty":2,"type_ko":"벨트","remark":"2013년식"},
    {"id":"PT-007","group":"35","name_ko":"V벨트 LC-104","part_number":"CA00008471A","qty":1,"type_ko":"벨트","remark":"2013년식"},
    {"id":"PT-008","group":"74","name_ko":"V벨트 LB37","part_number":"CA00003665A","qty":1,"type_ko":"벨트"},
    {"id":"PT-009","group":"75","name_ko":"V벨트 LC67 (GREEN)","part_number":"CA00006486A","qty":1,"type_ko":"벨트"},
    {"id":"PT-010","group":"158","name_ko":"크롤러 56×550","part_number":"CA00008197A","qty":2,"type_ko":"크롤러","remark":"2013년식"},
    {"id":"PT-011","group":"158","name_ko":"스프로켓 90×8T","part_number":"CAOOOO4486A","qty":2,"type_ko":"스프로켓"},
    {"id":"PT-012","group":"158","name_ko":"크롤러가이드","part_number":"CA00004972A","qty":4,"type_ko":"가이드"},
    {"id":"PT-013","group":"158","name_ko":"크롤러가이드 E","part_number":"CA00004971A","qty":2,"type_ko":"가이드"},
    {"id":"PT-014","group":"158","name_ko":"크롤러가이드 F","part_number":"CA00004973A","qty":2,"type_ko":"가이드"}
  ],
  "notes_ko": [
    "부품번호 끝의 알파벳은 개정 횟수를 나타냅니다 (A=초판, B=1차 개정, ...).",
    "비고란의 연도는 적용 시점(적용 제조번호)을 의미합니다.",
    "부품번호가 없는 항목은 개별 판매하지 않으며 상위 레벨 조합 부품으로 주문해야 합니다.",
    "수요기에는 소모부품 주문이 폭주하므로 사전 준비를 권장합니다."
  ]
}
